CHANGELOG.md
README.md
gfzs/__init__.py
gfzs/__main__.py
gfzs/cli.py
gfzs/cmd/__init__.py
gfzs/cmd/demo.py
gfzs/cmd/edit.py
gfzs/cmd/init.py
gfzs/cmd/valid.py
gfzs/controller.py
gfzs/info.py
gfzs/model.py
gfzs/runtime/__init__.py
gfzs/runtime/config.py
gfzs/runtime/opts.py
gfzs/tty.py
gfzs/utils/__init__.py
gfzs/utils/color.py
gfzs/utils/debug.py
gfzs/utils/logger.py
gfzs/utils/markup.py
gfzs/utils/multibyte.py
gfzs/utils/text_wrapper.py
gfzs/views/__init__.py
gfzs/views/base.py
gfzs/views/footer.py
gfzs/views/header.py
gfzs/views/not_found.py
gfzs/views/paging.py
gfzs/views/search_result.py
gfzs-0.2.3.dist-info/entry_points.txt
gfzs-0.2.3.dist-info/LICENSE
gfzs-0.2.3.dist-info/WHEEL
gfzs-0.2.3.dist-info/METADATA
gfzs-0.2.3.dist-info/RECORD
