Metadata-Version: 2.1
Name: gfzs
Version: 0.2.3
Summary: Google Fuzzy Search
Home-page: https://github.com/yukihirop/gfzs
License: MIT
Keywords: google,fuzzy-finder,finder,curses,tui
Author: yukihirop
Author-email: te108186@gmail.com
Maintainer: yukihirop
Maintainer-email: te108186@gmail.com
Requires-Python: >=3.6,<4.0
Classifier: Environment :: Console :: Curses
Classifier: License :: OSI Approved :: MIT License
Classifier: Programming Language :: Python
Classifier: Programming Language :: Python :: 3
Classifier: Programming Language :: Python :: 3.6
Classifier: Programming Language :: Python :: 3.7
Classifier: Programming Language :: Python :: 3.8
Classifier: Programming Language :: Python :: 3.9
Classifier: Topic :: Text Processing :: Filters
Classifier: Topic :: Utilities
Requires-Dist: flatten-dict (>=0.3.0,<0.4.0)
Requires-Dist: fuzzywuzzy (>=0.18.0,<0.19.0)
Requires-Dist: python-Levenshtein (>=0.12.1,<0.13.0)
Project-URL: Repository, https://github.com/yukihirop/gfzs
